Workbook
Name AB: 'Technical sheet'!$C$27:$C$31
Name AD: 'Technical sheet'!$D$27
Name AE: 'Technical sheet'!$E$27:$E$31
Name AG: 'Technical sheet'!$F$27:$F$31
Name AL: 'Technical sheet'!$G$27:$G$31
Name AM: 'Technical sheet'!$H$27:$H$33
Name AR: 'Technical sheet'!$I$27:$I$31
Name AS: 'Technical sheet'!$J$27:$J$35
Name ASA: 'Technical sheet'!$C$45:$C$47
Name ASC: 'Technical sheet'!$D$45:$D$49
Name AT: 'Technical sheet'!$K$27:$K$30
Name AU: 'Technical sheet'!$L$27:$L$29
Name BB: 'Technical sheet'!$M$27:$M$34
Name BBA: 'Technical sheet'!$E$45:$E$48
Name BBF: 'Technical sheet'!$F$45:$F$46
Name BP: 'Technical sheet'!$N$27:$N$29
Name BR: 'Technical sheet'!$O$27:$O$31
Name BRA: 'Technical sheet'!$G$45:$G$49
Name BRE: 'Technical sheet'!$H$45:$H$48
Name BU: 'Technical sheet'!$P$27:$P$29
Name CA: 'Technical sheet'!$Q$27:$Q$33
Name CAC: 'Technical sheet'!$I$45:$I$46
Name CAD: 'Technical sheet'!$J$45:$J$46
Name CB: 'Technical sheet'!$R$27:$R$36
Name CBM: 'Technical sheet'!$K$45:$K$46
Name CBN: 'Technical sheet'!$L$45:$L$46
Name CC: 'Technical sheet'!$S$27:$S$29
Name CCH: 'Technical sheet'!$M$45:$M$46
Name CD: 'Technical sheet'!$T$27:$T$29
Name CE: 'Technical sheet'!$U$27:$U$31
Name CEA: 'Technical sheet'!$N$45:$N$54
Name CI: 'Technical sheet'!$V$27:$V$29
Name CK: 'Technical sheet'!$W$27:$W$33
Name CKB: 'Technical sheet'!$O$45:$O$47
Name CL: 'Technical sheet'!$X$27:$X$29
Name CM: 'Technical sheet'!$Y$27:$Y$29
Name CN: 'Technical sheet'!$Z$27:$Z$34
Name CNB: 'Technical sheet'!$P$45:$P$48
Name CP: 'Technical sheet'!$AA$27:$AA$32
Name CR: 'Technical sheet'!$AB$27:$AB$36
Name CS: 'Technical sheet'!$AC$27:$AC$30
Name CT: 'Technical sheet'!$AD$27:$AD$37
Name CU: 'Technical sheet'!$AE$27:$AE$31
Name DA: 'Technical sheet'!$AF$27:$AF$30
Name DE: 'Technical sheet'!$AG$27:$AG$30
Name DEA: 'Technical sheet'!$Q$45:$Q$48
Name DEB: 'Technical sheet'!$R$45:$R$46
Name DO: 'Technical sheet'!$AH$27:$AH$30
Name ED: 'Technical sheet'!$AJ$27:$AJ$31
Name EG: 'Technical sheet'!$AI$27:$AI$39
Name EGJ: 'Technical sheet'!$S$45:$S$47
Name EGO: 'Technical sheet'!$T$45:$T$47
Name EM: 'Technical sheet'!$AK$27:$AK$30
Name EMA: 'Technical sheet'!$U$45:$U$46
Name EN: 'Technical sheet'!$AL$27:$AL$30
Name EU: 'Technical sheet'!$AM$27:$AM$32
Name EX: 'Technical sheet'!$AN$27:$AN$31
Name EXB: 'Technical sheet'!$V$45:$V$47
Name EXC: 'Technical sheet'!$W$45:$W$47
Name FA: 'Technical sheet'!$AO$27:$AO$39

Sheet Инструкция
B1: Анкета по зарплатным данным 2025
B3: Уважаемые коллеги, рады приветствовать вас в обзоре заработных плат Lens Consulting 2025!
B4: Благодарим вас за время, уделенное участию в исследовании.
B5: В случае возникновения вопросов по заполнению наши консультанты с радостью помогут вам.
B6: Для участия в исследовании, пожалуйста, заполните две вкладки:
B7: Общая информация | C7: Общая информация о компании и контактном лице, заполняющем анкету
B8: Данные | C8: Зарплатные данные по каждому сотруднику. Для каждого столбца представлена инструкция по заполнению
B10: Обращаем ваше внимание, что все зарплатные данные предоставляются по состоянию на 01.05.2025. Крайний срок подачи данных - 23 июня 2025 г.
B12: Для заполнения отдельных разделов анкеты вам поможет информация, представленная на следующих вкладках:
B13: Каталог функций | C13: Коды и описание функций, подфункций, специализаций
B14: Грейды | C14: Описание грейдов (уровней), секторные примеры должностей
B15: Определения | C15: Описание терминов, типы LTIP программ
B16: Регионы | C16: Перечень регионов Обзора
B17: Предложения | C17: Ваши предложения по добавлению новых функций в каталог
